mattermost_notify/__init__.py
mattermost_notify/__version__.py
mattermost_notify/errors.py
mattermost_notify/git.py
mattermost_notify/parser.py
mattermost_notify/post.py
mattermost_notify/status.py
mattermost_notify-26.1.2.dist-info/METADATA
mattermost_notify-26.1.2.dist-info/WHEEL
mattermost_notify-26.1.2.dist-info/entry_points.txt
mattermost_notify-26.1.2.dist-info/licenses/LICENSE
mattermost_notify-26.1.2.dist-info/RECORD
