Metadata-Version: 2.4
Name: mattermost-notify
Version: 26.1.2
Summary: Python tool to post GitHub Action runs to mattermost
License: GPL-3.0-or-later
License-File: LICENSE
Author: Jaspar Stach
Author-email: jasp.stac@gmx.de
Requires-Python: >=3.9,<4.0
Classifier: Development Status :: 4 - Beta
Classifier: Environment :: Console
Classifier: Intended Audience :: Developers
Classifier: License :: OSI Approved :: GNU General Public License v3 or later (GPLv3+)
Classifier: Operating System :: OS Independent
Classifier: Programming Language :: Python :: 3
Classifier: Programming Language :: Python :: 3.9
Classifier: Programming Language :: Python :: 3.10
Classifier: Programming Language :: Python :: 3.11
Classifier: Programming Language :: Python :: 3.12
Classifier: Programming Language :: Python :: 3.13
Classifier: Programming Language :: Python :: 3.14
Classifier: Topic :: Software Development :: Libraries :: Python Modules
Requires-Dist: httpx (>=0.23.1)
Requires-Dist: pontos (>=22.7.7)
